LICENSE
MANIFEST.in
README.md
setup.py
allianceauth_mumble_tagger.egg-info/PKG-INFO
allianceauth_mumble_tagger.egg-info/SOURCES.txt
allianceauth_mumble_tagger.egg-info/dependency_links.txt
allianceauth_mumble_tagger.egg-info/requires.txt
allianceauth_mumble_tagger.egg-info/top_level.txt
mumbletagger/__init__.py
mumbletagger/admin.py
mumbletagger/app_settings.py
mumbletagger/apps.py
mumbletagger/auth_hooks.py
mumbletagger/models.py
mumbletagger/signals.py
mumbletagger/tasks.py
mumbletagger/tests.py
mumbletagger/urls.py
mumbletagger/views.py
mumbletagger/migrations/0001_initial.py
mumbletagger/migrations/__init__.py
mumbletagger/test/__init__.py
mumbletagger/test/test_tagging.py
tests/__init__.py
tests/celery.py
tests/test_settings.py
tests/urls.py
tests/views.py