Metadata-Version: 2.1
Name: allianceauth-mumble-tagger
Version: 0.0.1
Summary: Alliance Auth Plugin
Home-page: https://github.com/pvyParts/allianceauth-mumble-tagger
Author: ak
Author-email: ak@ak.auth
License: GNU General Public License v3 (GPLv3)
Platform: UNKNOWN
Classifier: Environment :: Web Environment
Classifier: Framework :: Django
Classifier: Intended Audience :: Developers
Classifier: License :: OSI Approved :: GNU General Public License v3 (GPLv3)
Classifier: Operating System :: OS Independent
Classifier: Programming Language :: Python :: 3.6
Classifier: Topic :: Internet :: WWW/HTTP
Classifier: Topic :: Internet :: WWW/HTTP :: Dynamic Content
